{
  "documents": [
    {
      "name": "Doc1",
      "active_sheet_index": 0,
      "sheets": [
        {
          "name": "Sheet1",
          "cells": {
            "8,7": " on the hunt for the deer",
            "0,0": "There area ddas  dsd d ad ",
            "1,2": "I am telling ",
            "1,0": "sda",
            "6,0": "dsad ",
            "6,1": "there ",
            "1,3": "you "
          },
          "row_heights": {
            "0": 128,
            "6": 81,
            "1": 116
          },
          "col_widths": {
            "4": 265,
            "0": 394,
            "2": 191
          }
        },
        {
          "name": "Taha bhai",
          "cells": {
            "31,12": "dasdas",
            "9,22": "3",
            "11,23": "2",
            "10,22": "4",
            "10,18": "1",
            "24,1": "f",
            "6,1": "gfdg",
            "0,17": "4",
            "0,3": "bhj",
            "11,10": "fds",
            "12,0": "cc",
            "13,0": "csc",
            "14,5": "dwa",
            "0,0": "dasa",
            "0,1": "cdsac",
            "0,2": "dcds",
            "10,7": "dasd",
            "5,3": "THE HFDSJfh fdsjf fkjvbdfkjbkjfnkbnvkjfdnvljdfhvjbhbf",
            "5,5": "vfnjvdbjfd",
            "5,6": "dsaf",
            "6,3": "here",
            "13,8": " dsa",
            "9,4": "dsadas",
            "15,8": "ds",
            "11,5": "dasd",
            "17,9": "THE HFDSJfh fdsjf ",
            "18,6": "dadsdadsndbahcbdkcks  tyjfjdn  fjodfjsh fner fskfsd",
            "18,9": "here",
            "5,4": "vbhfbd",
            "5,7": "dfvds",
            "5,8": "fdsgf",
            "5,9": "fgvdgfd",
            "5,10": "fgvdfg",
            "6,10": "fvds",
            "7,10": "dsvsd",
            "8,10": "dvds",
            "9,10": "vv"
          },
          "row_heights": {},
          "col_widths": {}
        },
        {
          "name": "Sheet3",
          "cells": {},
          "row_heights": {},
          "col_widths": {}
        }
      ]
    },
    {
      "name": "Untitled 3",
      "active_sheet_index": 0,
      "sheets": [
        {
          "name": "Sheet1",
          "cells": {},
          "row_heights": {},
          "col_widths": {}
        }
      ]
    },
    {
      "name": "Untitled 5",
      "active_sheet_index": 0,
      "sheets": [
        {
          "name": "Sheet1",
          "cells": {},
          "row_heights": {},
          "col_widths": {}
        }
      ]
    },
    {
      "name": "Untitled 5",
      "active_sheet_index": 1,
      "sheets": [
        {
          "name": "Sheet1",
          "cells": {},
          "row_heights": {},
          "col_widths": {}
        },
        {
          "name": "Sheet2",
          "cells": {},
          "row_heights": {},
          "col_widths": {}
        }
      ]
    },
    {
      "name": "Doc2",
      "active_sheet_index": 0,
      "sheets": [
        {
          "name": "Sheet1",
          "cells": {},
          "row_heights": {},
          "col_widths": {}
        }
      ]
    },
    {
      "name": "Untitled 7",
      "active_sheet_index": 0,
      "sheets": [
        {
          "name": "Sheet1",
          "cells": {},
          "row_heights": {},
          "col_widths": {}
        }
      ]
    },
    {
      "name": "Untitled 8",
      "active_sheet_index": 0,
      "sheets": [
        {
          "name": "Sheet1",
          "cells": {},
          "row_heights": {},
          "col_widths": {}
        }
      ]
    },
    {
      "name": "Untitled 9",
      "active_sheet_index": 1,
      "sheets": [
        {
          "name": "Sheet1",
          "cells": {},
          "row_heights": {},
          "col_widths": {}
        },
        {
          "name": "dwads",
          "cells": {},
          "row_heights": {},
          "col_widths": {}
        }
      ]
    },
    {
      "name": "Untitled 10",
      "active_sheet_index": 0,
      "sheets": [
        {
          "name": "Sheet1",
          "cells": {},
          "row_heights": {},
          "col_widths": {}
        }
      ]
    }
  ]
}